Workbook

Sheet README
A1: ФИНАНСОВАЯ МОДЕЛЬ ИНВЕСТИЦИОННОГО ПРОЕКТА
A3: ИНСТРУКЦИЯ ПО ИСПОЛЬЗОВАНИЮ МОДЕЛИ
A5: 1. 📊 ВВОД ДАННЫХ - лист «Ввод»
A6: • Заполните параметры в желтых ячейках
A7: • Модель автоматически пересчитает показатели
A9: 2. 🔄 УПРАВЛЕНИЕ СЦЕНАРИЯМИ - лист «Сценарии»
A10: • Выберите один из 3 сценариев
A11: • Все графики обновляются автоматически
A13: 3. 📈 РЕЗУЛЬТАТЫ - лист «Отчёт»
A14: • Ключевые метрики: NPV, IRR, срок окупаемости
A15: • Автоматический статус проекта
A17: ТЕХНИЧЕСКИЕ ХАРАКТЕРИСТИКИ:
... A22: Создано: 01.10.2025

Sheet Ввод
A1: ПАРАМЕТРЫ ИНВЕСТИЦИОННОГО ПРОЕКТА
A3: ОСНОВНЫЕ ПАРАМЕТРЫ ПРОЕКТА
A4: Название проекта: | B4: Производство экологичной упаковки
A5: Тип оборудования: | B5: Стандарт
A6: Начальные инвестиции (₽): | B6: 5000000
A7: Срок проекта (лет): | B7: 5
A8: Ставка дисконтирования (%): | B8: 12
A9: Налог на прибыль (%): | B9: 20
A11: ПРОИЗВОДСТВЕННЫЕ ПОКАЗАТЕЛИ
A12: Начальный объём производства (ед./год): | B12: 100000
A13: Годовой рост объёма (%): | B13: 5
A14: Цена за единицу (₽): | B14: 50
A15: Переменные издержки (₽/ед.): | B15: 25
A16: Постоянные издержки (₽/год): | B16: 1000000

Sheet Расчёты
A1: ФИНАНСОВЫЕ РАСЧЁТЫ
A3: Год | B3: Объём | C3: Выручка | D3: Переменные затраты | E3: Постоянные затраты | F3: Амортизация | G3: EBITDA | H3: Налог | I3: Чистая прибыль | J3: FCF | K3: Накопленный FCF
A4: 1 | B4: =Ввод!B10*(1+Ввод!B11)^0 | C4: =B4*Ввод!B12 | D4: =B4*Ввод!B13 | E4: =Ввод!B14 | F4: =Ввод!B5/5 | G4: =C4-D4-E4 | H4: =MAX(0,G4-F4)*Ввод!B8 | I4: =G4-H4 | J4: =I4+F4 | K4: =J4
A5: 2 | B5: =Ввод!B10*(1+Ввод!B11)^1 | C5: =B5*Ввод!B12 | D5: =B5*Ввод!B13 | E5: =Ввод!B14 | F5: =Ввод!B5/5 | G5: =C5-D5-E5 | H5: =MAX(0,G5-F5)*Ввод!B8 | I5: =G5-H5 | J5: =I5+F5 | K5: =K4+J5
A6: 3 | B6: =Ввод!B10*(1+Ввод!B11)^2 | C6: =B6*Ввод!B12 | D6: =B6*Ввод!B13 | E6: =Ввод!B14 | F6: =Ввод!B5/5 | G6: =C6-D6-E6 | H6: =MAX(0,G6-F6)*Ввод!B8 | I6: =G6-H6 | J6: =I6+F6 | K6: =K5+J6
A7: 4 | B7: =Ввод!B10*(1+Ввод!B11)^3 | C7: =B7*Ввод!B12 | D7: =B7*Ввод!B13 | E7: =Ввод!B14 | F7: =Ввод!B5/5 | G7: =C7-D7-E7 | H7: =MAX(0,G7-F7)*Ввод!B8 | I7: =G7-H7 | J7: =I7+F7 | K7: =K6+J7
A8: 5 | B8: =Ввод!B10*(1+Ввод!B11)^4 | C8: =B8*Ввод!B12 | D8: =B8*Ввод!B13 | E8: =Ввод!B14 | F8: =Ввод!B5/5 | G8: =C8-D8-E8 | H8: =MAX(0,G8-F8)*Ввод!B8 | I8: =G8-H8 | J8: =I8+F8 | K8: =K7+J8
A10: КЛЮЧЕВЫЕ ФИНАНСОВЫЕ МЕТРИКИ
A11: NPV (₽): | B11: =NPV(Ввод!B7/100,J4:J8)-Ввод!B5
A12: IRR (%): | B12: =IRR(({-Ввод!B5,J4:J8}))*100
A13: Срок окупаемости (лет): | B13: =MATCH(0,K4:K8,1)+(-INDEX(K4:K8,MATCH(0,K4:K8,1)-1))/INDEX(J4:J8,MATCH(0,K4:K8,1))
A14: Точка безубыточности (ед.): | B14: =Ввод!B14/(Ввод!B12-Ввод!B13)

Sheet Сценарии
A1: СЦЕНАРНЫЙ АНАЛИЗ
A3: ВЫБЕРИТЕ СЦЕНАРИЙ: | B3: Базовый
A5: ТАБЛИЦА СЦЕНАРИЕВ
A6: Сценарий | B6: Объём | C6: Цена | D6: Рост% | E6: Переменные
A7: Пессимистичный | B7: 80000 | C7: 45 | D7: 2 | E7: 28
A8: Базовый | B8: 100000 | C8: 50 | D8: 5 | E8: 25
A9: Оптимистичный | B9: 120000 | C9: 55 | D9: 8 | E9: 22

Sheet Отчёт
A1: ИНВЕСТИЦИОННЫЙ ОТЧЁТ
A3: Информация о проекте:
A4: Название проекта: | B4: =Ввод!B3
A5: Сценарий: | B5: =Сценарии!B3
A6: Дата анализа: | B6: 01.10.2025
A7: Срок проекта: | B7: =Ввод!B6 & ' лет'
A8: КЛЮЧЕВЫЕ МЕТРИКИ ПРОЕКТА
A9: NPV проекта: | B9: =Расчёты!B11 | C9: ₽
A10: Внутренняя норма доходности (IRR): | B10: =Расчёты!B12 | C10: %
A11: Срок окупаемости: | B11: =Расчёты!B13 | C11: лет
A12: Точка безубыточности: | B12: =Расчёты!B14 | C12: ед.
A14: СТАТУС ПРОЕКТА: | B14: =ЕСЛИ(Расчёты!B12>=15;"✅ РЕКОМЕНДУЕТСЯ";ЕСЛИ(Расчёты!B12>=10;"⚠️ ТРЕБУЕТ ДОРАБОТКИ";"❌ ОТКЛОНЁН"))
A16: 📤 ЭКСПОРТИРОВАТЬ ОТЧЁТ В PDF
